smartschoolapi_tkbstudios/__init__.py
smartschoolapi_tkbstudios/smartschool.py
smartschoolapi_tkbstudios-1.2.0.dist-info/METADATA
smartschoolapi_tkbstudios-1.2.0.dist-info/WHEEL
smartschoolapi_tkbstudios-1.2.0.dist-info/licenses/LICENSE
smartschoolapi_tkbstudios-1.2.0.dist-info/RECORD
