Metadata-Version: 2.3
Name: smartschoolapi_tkbstudios
Version: 1.2.0
Summary: A python package to interact with SmartSchool, a Belgian School Management System
Project-URL: Homepage, https://github.com/tkbstudios/SmartSchoolPyClient
Project-URL: Issues, https://github.com/tkbstudios/SmartSchoolPyClient/issues
Author-email: TKB Studios <tkbstudios@mail.tkbstudios.com>
License-File: LICENSE
Classifier: License :: OSI Approved :: MIT License
Classifier: Operating System :: OS Independent
Classifier: Programming Language :: Python :: 3
Requires-Python: >=3.12
